flask_model_validation/__init__.py
flask_model_validation/exceptions.py
flask_model_validation/expressions.py
flask_model_validation/extension.py
flask_model_validation/models/__init__.py
flask_model_validation/models/mixins.py
flask_model_validation/models/model.py
flask_model_validation/query.py
flask_model_validation/validation/__init__.py
flask_model_validation/validation/validate_colum.py
flask_model_validation/validation/validators.py
flask_model_validation-0.1.0.dist-info/METADATA
flask_model_validation-0.1.0.dist-info/WHEEL
flask_model_validation-0.1.0.dist-info/RECORD
