Metadata-Version: 2.1
Name: flask-model-validation
Version: 0.1.0
Summary: Extension for Flask-SQLALchemy that include validation for models, a easier way to query and more new features.
Home-page: https://github.com/sr1871/flask-model-validation
Author: sr1871
Author-email: sergioal18v@gmail.com
Requires-Python: >=3.11,<4.0
Classifier: Development Status :: 3 - Alpha
Classifier: Environment :: Web Environment
Classifier: Framework :: Flask
Classifier: Intended Audience :: Developers
Classifier: License :: OSI Approved :: BSD License
Classifier: Operating System :: OS Independent
Classifier: Programming Language :: Python
Classifier: Programming Language :: Python :: 3
Classifier: Programming Language :: Python :: 3.11
Requires-Dist: flask-sqlalchemy (>=3.0.3,<4.0.0)
Requires-Dist: python-slugify (>=8.0.1,<9.0.0)
Project-URL: Repository, https://github.com/sr1871/flask-model-validation
